[
  { "bowler": "RN ten Doeschate", "economy_rate": "4.00" },
  { "bowler": "J Yadav", "economy_rate": "4.14" },
  { "bowler": "V Kohli", "economy_rate": "5.45" },
  { "bowler": "R Ashwin", "economy_rate": "5.87" },
  { "bowler": "S Nadeem", "economy_rate": "6.14" },
  { "bowler": "Parvez Rasool", "economy_rate": "6.20" },
  { "bowler": "MC Henriques", "economy_rate": "6.56" },
  { "bowler": "Z Khan", "economy_rate": "6.58" },
  { "bowler": "M Vijay", "economy_rate": "7.00" },
  { "bowler": "GB Hogg", "economy_rate": "7.05" }
]
